{
  "info": {
    "name": "FIMS API (Unified Backend)",
    "description": "Postman collection to test the FIMS API (Do-It-Now + Mobile View)",
    "schema": "https://schema.getpostman.com/json/collection/v2.1.0/collection.json"
  },
  "item": [
    {
      "name": "Health Check",
      "request": {
        "method": "GET",
        "header": [],
        "url": {
          "raw": "http://localhost:5000/api/health",
          "protocol": "http",
          "host": ["localhost"],
          "port": "5000",
          "path": ["api", "health"]
        }
      }
    },
    {
      "name": "Stations",
      "item": [
        {
          "name": "Get All Stations",
          "request": {
            "method": "GET",
            "header": [],
            "url": {
              "raw": "http://localhost:5000/api/stations",
              "protocol": "http",
              "host": ["localhost"],
              "port": "5000",
              "path": ["api", "stations"]
            }
          }
        },
        {
          "name": "Get Station by ID",
          "request": {
            "method": "GET",
            "header": [],
            "url": {
              "raw": "http://localhost:5000/api/stations/REPLACE_WITH_ID",
              "protocol": "http",
              "host": ["localhost"],
              "port": "5000",
              "path": ["api", "stations", "REPLACE_WITH_ID"]
            }
          }
        },
        {
          "name": "Create Station",
          "request": {
            "method": "POST",
            "header": [
              {
                "key": "Content-Type",
                "value": "application/json"
              }
            ],
            "body": {
              "mode": "raw",
              "raw": "{\n    \"code\": \"TBGS00999\",\n    \"name\": \"محطة اختبار\",\n    \"region\": \"تبوك\",\n    \"activity\": \"محطة وقود\",\n    \"lat\": \"28.3740\",\n    \"lng\": \"36.4790\"\n}"
            },
            "url": {
              "raw": "http://localhost:5000/api/stations",
              "protocol": "http",
              "host": ["localhost"],
              "port": "5000",
              "path": ["api", "stations"]
            }
          }
        },
        {
          "name": "Update Station",
          "request": {
            "method": "PUT",
            "header": [
              {
                "key": "Content-Type",
                "value": "application/json"
              }
            ],
            "body": {
              "mode": "raw",
              "raw": "{\n    \"name\": \"محطة اختبار (محدثة)\"\n}"
            },
            "url": {
              "raw": "http://localhost:5000/api/stations/REPLACE_WITH_ID",
              "protocol": "http",
              "host": ["localhost"],
              "port": "5000",
              "path": ["api", "stations", "REPLACE_WITH_ID"]
            }
          }
        },
        {
          "name": "Delete Station",
          "request": {
            "method": "DELETE",
            "header": [],
            "url": {
              "raw": "http://localhost:5000/api/stations/REPLACE_WITH_ID",
              "protocol": "http",
              "host": ["localhost"],
              "port": "5000",
              "path": ["api", "stations", "REPLACE_WITH_ID"]
            }
          }
        }
      ]
    },
    {
      "name": "Visits",
      "item": [
        {
          "name": "Get All Visits",
          "request": {
            "method": "GET",
            "header": [],
            "url": {
              "raw": "http://localhost:5000/api/visits",
              "protocol": "http",
              "host": ["localhost"],
              "port": "5000",
              "path": ["api", "visits"]
            }
          }
        },
        {
          "name": "Get Dashboard Stats",
          "request": {
            "method": "GET",
            "header": [],
            "url": {
              "raw": "http://localhost:5000/api/visits/stats",
              "protocol": "http",
              "host": ["localhost"],
              "port": "5000",
              "path": ["api", "visits", "stats"]
            }
          }
        },
        {
          "name": "Get Visit by ID",
          "request": {
            "method": "GET",
            "header": [],
            "url": {
              "raw": "http://localhost:5000/api/visits/REPLACE_WITH_ID",
              "protocol": "http",
              "host": ["localhost"],
              "port": "5000",
              "path": ["api", "visits", "REPLACE_WITH_ID"]
            }
          }
        },
        {
          "name": "Create Visit",
          "request": {
            "method": "POST",
            "header": [
              {
                "key": "Content-Type",
                "value": "application/json"
              }
            ],
            "body": {
              "mode": "raw",
              "raw": "{\n    \"stationId\": \"REPLACE_WITH_STATION_ID\",\n    \"type\": \"متابعة دورية\",\n    \"date\": \"2026-05-05T00:00:00Z\",\n    \"inspectors\": [\"يوسف ناصر\"],\n    \"refNumber\": \"REF-2026-TEST\",\n    \"notes\": [\n        {\n            \"element\": \"مضخة رقم 1\",\n            \"description\": \"تسريب خفيف في الخرطوم\",\n            \"severity\": \"مخالفة\",\n            \"urgent\": true,\n            \"recurring\": false,\n            \"correctiveAction\": \"استبدال الخرطوم فوراً\"\n        }\n    ]\n}"
            },
            "url": {
              "raw": "http://localhost:5000/api/visits",
              "protocol": "http",
              "host": ["localhost"],
              "port": "5000",
              "path": ["api", "visits"]
            }
          }
        }
      ]
    },
    {
      "name": "Inspectors",
      "item": [
        {
          "name": "Get All Inspectors",
          "request": {
            "method": "GET",
            "header": [],
            "url": {
              "raw": "http://localhost:5000/api/inspectors",
              "protocol": "http",
              "host": ["localhost"],
              "port": "5000",
              "path": ["api", "inspectors"]
            }
          }
        },
        {
          "name": "Create Inspector",
          "request": {
            "method": "POST",
            "header": [
              {
                "key": "Content-Type",
                "value": "application/json"
              }
            ],
            "body": {
              "mode": "raw",
              "raw": "{\n    \"name\": \"مفتش جديد\",\n    \"role\": \"inspector\"\n}"
            },
            "url": {
              "raw": "http://localhost:5000/api/inspectors",
              "protocol": "http",
              "host": ["localhost"],
              "port": "5000",
              "path": ["api", "inspectors"]
            }
          }
        }
      ]
    },
    {
      "name": "Settings",
      "item": [
        {
          "name": "Get Settings",
          "request": {
            "method": "GET",
            "header": [],
            "url": {
              "raw": "http://localhost:5000/api/settings",
              "protocol": "http",
              "host": ["localhost"],
              "port": "5000",
              "path": ["api", "settings"]
            }
          }
        },
        {
          "name": "Update Setting",
          "request": {
            "method": "PUT",
            "header": [
              {
                "key": "Content-Type",
                "value": "application/json"
              }
            ],
            "body": {
              "mode": "raw",
              "raw": "{\n    \"value\": [\"السلامة\", \"متابعة دورية\", \"مسح ميداني\", \"نوع جديد\"]\n}"
            },
            "url": {
              "raw": "http://localhost:5000/api/settings/visitTypes",
              "protocol": "http",
              "host": ["localhost"],
              "port": "5000",
              "path": ["api", "settings", "visitTypes"]
            }
          }
        }
      ]
    },
    {
      "name": "Upload",
      "item": [
        {
          "name": "Upload Image",
          "request": {
            "method": "POST",
            "header": [],
            "body": {
              "mode": "formdata",
              "formdata": [
                {
                  "key": "image",
                  "type": "file",
                  "src": []
                }
              ]
            },
            "url": {
              "raw": "http://localhost:5000/api/upload/image",
              "protocol": "http",
              "host": ["localhost"],
              "port": "5000",
              "path": ["api", "upload", "image"]
            }
          }
        },
        {
          "name": "Upload Bulk Excel",
          "request": {
            "method": "POST",
            "header": [],
            "body": {
              "mode": "formdata",
              "formdata": [
                {
                  "key": "file",
                  "type": "file",
                  "src": []
                }
              ]
            },
            "url": {
              "raw": "http://localhost:5000/api/stations/bulk",
              "protocol": "http",
              "host": ["localhost"],
              "port": "5000",
              "path": ["api", "stations", "bulk"]
            }
          }
        }
      ]
    }
  ]
}
